fastfeedparser/__init__.py
fastfeedparser/main.py
fastfeedparser-0.4.4.dist-info/LICENSE
fastfeedparser-0.4.4.dist-info/METADATA
fastfeedparser-0.4.4.dist-info/WHEEL
fastfeedparser-0.4.4.dist-info/top_level.txt
fastfeedparser-0.4.4.dist-info/RECORD
