Metadata-Version: 2.1
Name: fastfeedparser
Version: 0.4.4
Summary: High performance RSS, Atom, JSON and RDF feed parser in Python
Home-page: https://github.com/kagisearch/fastfeedparser
Author: Vladimir Prelovac
Author-email: vlad@kagi.com
Project-URL: Bug Tracker, https://github.com/kagisearch/fastfeedparser/issues
Classifier: Programming Language :: Python :: 3
Classifier: Programming Language :: Python :: 3.7
Classifier: Programming Language :: Python :: 3.8
Classifier: Programming Language :: Python :: 3.9
Classifier: Programming Language :: Python :: 3.10
Classifier: Programming Language :: Python :: 3.11
Classifier: Programming Language :: Python :: 3.12
Classifier: Programming Language :: Python :: 3.13
Classifier: License :: OSI Approved :: MIT License
Classifier: Operating System :: OS Independent
Classifier: Development Status :: 4 - Beta
Classifier: Intended Audience :: Developers
Classifier: Topic :: Software Development :: Libraries :: Python Modules
Classifier: Topic :: Text Processing :: Markup :: XML
Requires-Python: >=3.7
License-File: LICENSE
Requires-Dist: dateparser
Requires-Dist: lxml
Requires-Dist: python-dateutil
Requires-Dist: brotli
